{
  "stats": {
    "suites": 1,
    "tests": 52,
    "passes": 52,
    "pending": 0,
    "failures": 0,
    "start": "2021-01-08T01:35:26.098Z",
    "passPercent": 100,
    "pendingPercent": 0,
    "other": 0,
    "hasOther": false,
    "skipped": 0,
    "hasSkipped": false,
    "duration": 34680,
    "end": "2021-01-08T01:36:35.906Z"
  },
  "suites": {
    "title": "",
    "ctx": {},
    "suites": [
      {
        "title": "sample/testx : chrome",
        "ctx": {
          "_runnable": {
            "title": "\"after all\" hook",
            "body": "function(){\n                return this.driver.close();\n            }",
            "async": 0,
            "sync": true,
            "_timeout": 600000,
            "_slow": 1000,
            "_enableTimeouts": true,
            "timedOut": false,
            "_retries": -1,
            "_currentRetry": 0,
            "pending": false,
            "type": "hook",
            "parent": "~suites~suites~0",
            "ctx": "~suites~suites~0~ctx",
            "file": "E:\\test13\\sample\\testx.js",
            "_events": {},
            "_eventsCount": 1,
            "timer": {
              "_called": false,
              "_idleTimeout": -1,
              "_idlePrev": null,
              "_idleNext": null,
              "_idleStart": 81837,
              "_onTimeout": null,
              "_repeat": null,
              "_destroyed": false
            },
            "duration": 158,
            "_error": null
          },
          "test": "~suites~suites~0~ctx~_runnable",
          "driver": "[object Promise]",
          "testVars": {},
          "screenshotPath": "E:\\test13/reports/screenshots/sample",
          "diffbasePath": "E:\\test13/reports/diffbase/sample",
          "caseName": "testx_chrome",
          "stepId": 52
        },
        "suites": [],
        "tests": [
          {
            "title": "url: https://itest.clife.net/platformAdmin/aFan/index.html#/login",
            "fullTitle": "sample/testx : chrome -- url: https://itest.clife.net/platformAdmin/aFan/index.html#/login",
            "duration": 1354,
            "state": "passed",
            "pass": true,
            "fail": false,
            "pending": false,
            "context": "\"./screenshots/sample/testx_chrome_1.png\"",
            "code": "async function(){\n        await driver.url(_(`https://itest.clife.net/platformAdmin/aFan/index.html#/login`));",
            "uuid": "ad69d1e0-46b4-41c8-9f75-ba8ffe6bb461",
            "skipped": false
          },
          {
            "title": "waitBody: ",
            "fullTitle": "sample/testx : chrome -- waitBody: ",
            "duration": 529,
            "state": "passed",
            "pass": true,
            "fail": false,
            "pending": false,
            "context": "\"./screenshots/sample/testx_chrome_2.png\"",
            "code": "async function(){\n        await driver.sleep(500)\n.wait('body', 30000)\n.html()\n.then(function(code){\n            isPageError(code)\n.should.be.false;\n        });",
            "uuid": "3ce974fd-f777-4298-8dd2-75b7b65a0b2d",
            "skipped": false
          },
          {
            "title": "click: #normal_login_username, 73, 13, 0",
            "fullTitle": "sample/testx : chrome -- click: #normal_login_username, 73, 13, 0",
            "duration": 668,
            "state": "passed",
            "pass": true,
            "fail": false,
            "pending": false,
            "context": "\"./screenshots/sample/testx_chrome_3.png\"",
            "code": "async function(){\n        await driver.sleep(300)\n.wait('#normal_login_username', 30000)\n               .sleep(300)\n.mouseMove(73, 13)\n.click(0);",
            "uuid": "e7ac28b6-c9a1-45e8-9b42-456e79ab00aa",
            "skipped": false
          },
          {
            "title": "sendKeys: 13128912709",
            "fullTitle": "sample/testx : chrome -- sendKeys: 13128912709",
            "duration": 56,
            "state": "passed",
            "pass": true,
            "fail": false,
            "pending": false,
            "context": "\"./screenshots/sample/testx_chrome_4.png\"",
            "code": "async function(){\n        await driver.sendKeys('13128912709');",
            "uuid": "74f4cb42-1de4-40ac-857c-098cdee2885b",
            "skipped": false
          },
          {
            "title": "click: #normal_login_password, 73, 29, 0",
            "fullTitle": "sample/testx : chrome -- click: #normal_login_password, 73, 29, 0",
            "duration": 655,
            "state": "passed",
            "pass": true,
            "fail": false,
            "pending": false,
            "context": "\"./screenshots/sample/testx_chrome_5.png\"",
            "code": "async function(){\n        await driver.sleep(300)\n.wait('#normal_login_password', 30000)\n               .sleep(300)\n.mouseMove(73, 29)\n.click(0);",
            "uuid": "18e15cdf-2caf-4c09-b343-6523d2d2a3e8",
            "skipped": false
          },
          {
            "title": "sendKeys: 123456",
            "fullTitle": "sample/testx : chrome -- sendKeys: 123456",
            "duration": 31,
            "state": "passed",
            "pass": true,
            "fail": false,
            "pending": false,
            "context": "\"./screenshots/sample/testx_chrome_6.png\"",
            "code": "async function(){\n        await driver.sendKeys('123456');",
            "uuid": "ef90ec37-19a9-4099-817b-ec5166922e39",
            "skipped": false
          },
          {
            "title": "click: 登 录 ( #container button, 140, 13, 0 )",
            "fullTitle": "sample/testx : chrome -- click: 登 录 ( #container button, 140, 13, 0 )",
            "duration": 659,
            "state": "passed",
            "pass": true,
            "fail": false,
            "pending": false,
            "context": "\"./screenshots/sample/testx_chrome_7.png\"",
            "code": "async function(){\n        await driver.sleep(300)\n.wait('#container button', 30000)\n               .sleep(300)\n.mouseMove(140, 13)\n.click(0);",
            "uuid": "0cf255a3-d949-45d0-b2cc-5024ce150232",
            "skipped": false
          },
          {
            "title": "click: 合作商品 ( #container li[role=\"menuitem\"]:nth-child(5) > div.ant-menu-submenu-title, 111, 20, 0 )",
            "fullTitle": "sample/testx : chrome -- click: 合作商品 ( #container li[role=\"menuitem\"]:nth-child(5) > div.ant-menu-submenu-title, 111, 20, 0 )",
            "duration": 854,
            "state": "passed",
            "pass": true,
            "fail": false,
            "pending": false,
            "context": "\"./screenshots/sample/testx_chrome_8.png\"",
            "code": "async function(){\n        await driver.sleep(300)\n.wait('#container li[role=\"menuitem\"]:nth-child(5) > div.ant-menu-submenu-title', 30000)\n               .sleep(300)\n.mouseMove(111, 20)\n.click(0);",
            "uuid": "f0d55929-a7e5-4bab-8cbc-18e541aa5690",
            "skipped": false
          },
          {
            "title": "click: 合作商品管理 ( //a[text()=\"合作商品管理\"], 65, 17, 0 )",
            "fullTitle": "sample/testx : chrome -- click: 合作商品管理 ( //a[text()=\"合作商品管理\"], 65, 17, 0 )",
            "duration": 869,
            "state": "passed",
            "pass": true,
            "fail": false,
            "pending": false,
            "context": "\"./screenshots/sample/testx_chrome_9.png\"",
            "code": "async function(){\n        await driver.sleep(300)\n.wait('//a[text()=\"合作商品管理\"]', 30000)\n               .sleep(300)\n.mouseMove(65, 17)\n.click(0);",
            "uuid": "50edf6f8-8c82-4c11-b43b-9c33753f4c22",
            "skipped": false
          },
          {
            "title": "sleep: 2000",
            "fullTitle": "sample/testx : chrome -- sleep: 2000",
            "duration": 1999,
            "state": "passed",
            "pass": true,
            "fail": false,
            "pending": false,
            "context": "\"./screenshots/sample/testx_chrome_10.png\"",
            "code": "async function(){\n        await driver.sleep(2000);",
            "uuid": "6e48dc4f-0188-4479-bd34-46691942f429",
            "skipped": false
          },
          {
            "title": "click: 新 建 ( #container button.ant-btn-primary, 24, 19, 0 )",
            "fullTitle": "sample/testx : chrome -- click: 新 建 ( #container button.ant-btn-primary, 24, 19, 0 )",
            "duration": 661,
            "state": "passed",
            "pass": true,
            "fail": false,
            "pending": false,
            "context": "\"./screenshots/sample/testx_chrome_11.png\"",
            "code": "async function(){\n        await driver.sleep(300)\n.wait('#container button.ant-btn-primary', 30000)\n               .sleep(300)\n.mouseMove(24, 19)\n.click(0);",
            "uuid": "cb993877-4863-47e5-a4a7-f161d34e9180",
            "skipped": false
          },
          {
            "title": "click: 商品名称 ( #add_goodsName, 56, 22, 0 )",
            "fullTitle": "sample/testx : chrome -- click: 商品名称 ( #add_goodsName, 56, 22, 0 )",
            "duration": 660,
            "state": "passed",
            "pass": true,
            "fail": false,
            "pending": false,
            "context": "\"./screenshots/sample/testx_chrome_12.png\"",
            "code": "async function(){\n        await driver.sleep(300)\n.wait('#add_goodsName', 30000)\n               .sleep(300)\n.mouseMove(56, 22)\n.click(0);",
            "uuid": "9d3d3e4c-eb3a-4a63-a04d-60fe105231a5",
            "skipped": false
          },
          {
            "title": "sendKeys: UIzi{BACK_SPACE}{BACK_SPACE}自动化新建合作商品",
            "fullTitle": "sample/testx : chrome -- sendKeys: UIzi{BACK_SPACE}{BACK_SPACE}自动化新建合作商品",
            "duration": 83,
            "state": "passed",
            "pass": true,
            "fail": false,
            "pending": false,
            "context": "\"./screenshots/sample/testx_chrome_13.png\"",
            "code": "async function(){\n        await driver.sendKeys('UIzi{BACK_SPACE}{BACK_SPACE}自动化新建合作商品');",
            "uuid": "421b277d-3289-430c-a874-89bcd0757d5f",
            "skipped": false
          },
          {
            "title": "scrollElementTo: #add_goodsName, 0, 0",
            "fullTitle": "sample/testx : chrome -- scrollElementTo: #add_goodsName, 0, 0",
            "duration": 620,
            "state": "passed",
            "pass": true,
            "fail": false,
            "pending": false,
            "context": "\"./screenshots/sample/testx_chrome_14.png\"",
            "code": "async function(){\n        await driver.sleep(300)\n.wait('#add_goodsName', 30000)\n               .sleep(300)\n.scrollElementTo(0, 0);",
            "uuid": "70ef83e6-d63a-4543-8bc2-3b6a96d6786c",
            "skipped": false
          },
          {
            "title": "click: 支持不支持 ( #container div:nth-child(3) > div.ant-col-sm-15 > div.ant-form-item-control, 335, 2, 0 )",
            "fullTitle": "sample/testx : chrome -- click: 支持不支持 ( #container div:nth-child(3) > div.ant-col-sm-15 > div.ant-form-item-control, 335, 2, 0 )",
            "duration": 657,
            "state": "passed",
            "pass": true,
            "fail": false,
            "pending": false,
            "context": "\"./screenshots/sample/testx_chrome_15.png\"",
            "code": "async function(){\n        await driver.sleep(300)\n.wait('#container div:nth-child(3) > div.ant-col-sm-15 > div.ant-form-item-control', 30000)\n               .sleep(300)\n.mouseMove(335, 2)\n.click(0);",
            "uuid": "59b229f3-f9f3-4446-9ac7-6c0642dca68e",
            "skipped": false
          },
          {
            "title": "scrollElementTo: #container section > section.ant-layout, 0, 100",
            "fullTitle": "sample/testx : chrome -- scrollElementTo: #container section > section.ant-layout, 0, 100",
            "duration": 624,
            "state": "passed",
            "pass": true,
            "fail": false,
            "pending": false,
            "context": "\"./screenshots/sample/testx_chrome_16.png\"",
            "code": "async function(){\n        await driver.sleep(300)\n.wait('#container section > section.ant-layout', 30000)\n               .sleep(300)\n.scrollElementTo(0, 100);",
            "uuid": "cf5b3ec0-618b-48e3-a627-3e790eac1080",
            "skipped": false
          },
          {
            "title": "click: 商品价格 ( #add_goodsPrice, 42, 18, 0 )",
            "fullTitle": "sample/testx : chrome -- click: 商品价格 ( #add_goodsPrice, 42, 18, 0 )",
            "duration": 648,
            "state": "passed",
            "pass": true,
            "fail": false,
            "pending": false,
            "context": "\"./screenshots/sample/testx_chrome_17.png\"",
            "code": "async function(){\n        await driver.sleep(300)\n.wait('#add_goodsPrice', 30000)\n               .sleep(300)\n.mouseMove(42, 18)\n.click(0);",
            "uuid": "8a7828af-d84b-4b46-b12a-fc8fc8b856a1",
            "skipped": false
          },
          {
            "title": "sendKeys: 1999",
            "fullTitle": "sample/testx : chrome -- sendKeys: 1999",
            "duration": 24,
            "state": "passed",
            "pass": true,
            "fail": false,
            "pending": false,
            "context": "\"./screenshots/sample/testx_chrome_18.png\"",
            "code": "async function(){\n        await driver.sendKeys('1999');",
            "uuid": "655337ad-1d2b-48d7-a55c-d9efe0b38489",
            "skipped": false
          },
          {
            "title": "click: #container span.upload-component, 213, 21, 0",
            "fullTitle": "sample/testx : chrome -- click: #container span.upload-component, 213, 21, 0",
            "duration": 639,
            "state": "passed",
            "pass": true,
            "fail": false,
            "pending": false,
            "context": "\"./screenshots/sample/testx_chrome_19.png\"",
            "code": "async function(){\n        await driver.sleep(300)\n.wait('#container span.upload-component', 30000)\n               .sleep(300)\n.mouseMove(213, 21)\n.click(0);",
            "uuid": "93c6a9a5-b422-4e9b-a1c8-a4f1768465ec",
            "skipped": false
          },
          {
            "title": "click: input[value=\"1\"], 4, 4, 0",
            "fullTitle": "sample/testx : chrome -- click: input[value=\"1\"], 4, 4, 0",
            "duration": 657,
            "state": "passed",
            "pass": true,
            "fail": false,
            "pending": false,
            "context": "\"./screenshots/sample/testx_chrome_20.png\"",
            "code": "async function(){\n        await driver.sleep(300)\n.wait('input[value=\"1\"]', 30000)\n               .sleep(300)\n.mouseMove(4, 4)\n.click(0);",
            "uuid": "054e70a1-31a7-400b-a0b9-9c26d0183444",
            "skipped": false
          },
          {
            "title": "uploadFile: input[type=\"file\"], 1.jpg",
            "fullTitle": "sample/testx : chrome -- uploadFile: input[type=\"file\"], 1.jpg",
            "duration": 799,
            "state": "passed",
            "pass": true,
            "fail": false,
            "pending": false,
            "context": "\"./screenshots/sample/testx_chrome_21.png\"",
            "code": "async function(){\n        await driver.sleep(300)\n.wait('input[type=\"file\"]', {timeout: 30000, displayed: false})\n               .sleep(300)\n.uploadFile(rootPath+'/uploadfiles/1.jpg');",
            "uuid": "c02b642f-06c8-4bad-9f2c-15dc2cb9029f",
            "skipped": false
          },
          {
            "title": "scrollElementTo: #container section > section.ant-layout, 0, 484",
            "fullTitle": "sample/testx : chrome -- scrollElementTo: #container section > section.ant-layout, 0, 484",
            "duration": 629,
            "state": "passed",
            "pass": true,
            "fail": false,
            "pending": false,
            "context": "\"./screenshots/sample/testx_chrome_22.png\"",
            "code": "async function(){\n        await driver.sleep(300)\n.wait('#container section > section.ant-layout', 30000)\n               .sleep(300)\n.scrollElementTo(0, 484);",
            "uuid": "b4ba215a-98b8-47ef-aa13-9e2ac32d8ccf",
            "skipped": false
          },
          {
            "title": "sleep: 5000",
            "fullTitle": "sample/testx : chrome -- sleep: 5000",
            "duration": 5001,
            "state": "passed",
            "pass": true,
            "fail": false,
            "pending": false,
            "context": "\"./screenshots/sample/testx_chrome_23.png\"",
            "code": "async function(){\n        await driver.sleep(5000);",
            "uuid": "2d3ee9e2-5679-4a1b-9a7f-ced6e5e2ba55",
            "skipped": false
          },
          {
            "title": "switchFrame: #add_content iframe",
            "fullTitle": "sample/testx : chrome -- switchFrame: #add_content iframe",
            "duration": 51,
            "state": "passed",
            "pass": true,
            "fail": false,
            "pending": false,
            "context": "\"./screenshots/sample/testx_chrome_24.png\"",
            "code": "async function(){\n        await driver.switchFrame(null)\n               .wait('#add_content iframe', 30000)\n.then(function(element){\n                   return this.switchFrame(element)\n.wait('body');\n               });",
            "uuid": "df6c465b-37bb-4747-af1d-a03e6910997b",
            "skipped": false
          },
          {
            "title": "click: body, 46, 54, 0",
            "fullTitle": "sample/testx : chrome -- click: body, 46, 54, 0",
            "duration": 681,
            "state": "passed",
            "pass": true,
            "fail": false,
            "pending": false,
            "context": "\"./screenshots/sample/testx_chrome_25.png\"",
            "code": "async function(){\n        await driver.sleep(300)\n.wait('body', 30000)\n               .sleep(300)\n.mouseMove(46, 54)\n.click(0);",
            "uuid": "c8d1d85a-93b3-4178-8850-569b400ff787",
            "skipped": false
          },
          {
            "title": "sendKeys: 哈哈哈",
            "fullTitle": "sample/testx : chrome -- sendKeys: 哈哈哈",
            "duration": 32,
            "state": "passed",
            "pass": true,
            "fail": false,
            "pending": false,
            "context": "\"./screenshots/sample/testx_chrome_26.png\"",
            "code": "async function(){\n        await driver.sendKeys('哈哈哈');",
            "uuid": "1b2cc786-9150-4500-a6c1-37927b55a15d",
            "skipped": false
          },
          {
            "title": "switchFrame: null",
            "fullTitle": "sample/testx : chrome -- switchFrame: null",
            "duration": 4,
            "state": "passed",
            "pass": true,
            "fail": false,
            "pending": false,
            "context": "\"./screenshots/sample/testx_chrome_27.png\"",
            "code": "async function(){\n        await driver.switchFrame(null);",
            "uuid": "1de5a4ab-737e-4be0-a231-8a592f4614af",
            "skipped": false
          },
          {
            "title": "click: 确 定 ( #container button.ant-btn-primary, 34, 16, 0 )",
            "fullTitle": "sample/testx : chrome -- click: 确 定 ( #container button.ant-btn-primary, 34, 16, 0 )",
            "duration": 658,
            "state": "passed",
            "pass": true,
            "fail": false,
            "pending": false,
            "context": "\"./screenshots/sample/testx_chrome_28.png\"",
            "code": "async function(){\n        await driver.sleep(300)\n.wait('#container button.ant-btn-primary', 30000)\n               .sleep(300)\n.mouseMove(34, 16)\n.click(0);",
            "uuid": "f73b4e26-67eb-4c49-b0b3-7c922242cde2",
            "skipped": false
          },
          {
            "title": "scrollElementTo: #container section > section.ant-layout, 0, 0",
            "fullTitle": "sample/testx : chrome -- scrollElementTo: #container section > section.ant-layout, 0, 0",
            "duration": 621,
            "state": "passed",
            "pass": true,
            "fail": false,
            "pending": false,
            "context": "\"./screenshots/sample/testx_chrome_29.png\"",
            "code": "async function(){\n        await driver.sleep(300)\n.wait('#container section > section.ant-layout', 30000)\n               .sleep(300)\n.scrollElementTo(0, 0);",
            "uuid": "e6ee6bbe-33e3-4f85-91f4-b388aaa0cc72",
            "skipped": false
          },
          {
            "title": "click: 下架商品 ( //div[text()=\"下架商品\"], 45, 14, 0 )",
            "fullTitle": "sample/testx : chrome -- click: 下架商品 ( //div[text()=\"下架商品\"], 45, 14, 0 )",
            "duration": 685,
            "state": "passed",
            "pass": true,
            "fail": false,
            "pending": false,
            "context": "\"./screenshots/sample/testx_chrome_30.png\"",
            "code": "async function(){\n        await driver.sleep(300)\n.wait('//div[text()=\"下架商品\"]', 30000)\n               .sleep(300)\n.mouseMove(45, 14)\n.click(0);",
            "uuid": "84245956-41c9-4954-a890-7e6bcd5a0b40",
            "skipped": false
          },
          {
            "title": "expect: text, //div[text()=\"UI自动化新建合作商...\"], equal, UI自动化新建合作商...",
            "fullTitle": "sample/testx : chrome -- expect: text, //div[text()=\"UI自动化新建合作商...\"], equal, UI自动化新建合作商...",
            "duration": 359,
            "state": "passed",
            "pass": true,
            "fail": false,
            "pending": false,
            "context": "\"./screenshots/sample/testx_chrome_31.png\"",
            "code": "async function(){\n        await driver.sleep(300)\n.wait('//div[text()=\"UI自动化新建合作商...\"]', 30000)\n            .text()\n            .should.not.be.a('error')\n            .should.equal(_(`UI自动化新建合作商...`));",
            "uuid": "502be60a-bf8e-4fb8-98c5-a9c18dca79a6",
            "skipped": false
          },
          {
            "title": "mouseDown: UI自动化新建合作商..... ( //div[text()=\"UI自动化新建合作商...\"], 3, 15, 0 )",
            "fullTitle": "sample/testx : chrome -- mouseDown: UI自动化新建合作商..... ( //div[text()=\"UI自动化新建合作商...\"], 3, 15, 0 )",
            "duration": 633,
            "state": "passed",
            "pass": true,
            "fail": false,
            "pending": false,
            "context": "\"./screenshots/sample/testx_chrome_32.png\"",
            "code": "async function(){\n        await driver.sleep(300)\n.wait('//div[text()=\"UI自动化新建合作商...\"]', 30000)\n               .sleep(300)\n.mouseMove(3, 15)\n.mouseDown(0);",
            "uuid": "e5f9994e-b5e3-47e2-8317-a211b7de3c42",
            "skipped": false
          },
          {
            "title": "mouseUp: UI自动化新建合作商..... ( //div[text()=\"UI自动化新建合作商...\"], 81, 10, 0 )",
            "fullTitle": "sample/testx : chrome -- mouseUp: UI自动化新建合作商..... ( //div[text()=\"UI自动化新建合作商...\"], 81, 10, 0 )",
            "duration": 701,
            "state": "passed",
            "pass": true,
            "fail": false,
            "pending": false,
            "context": "\"./screenshots/sample/testx_chrome_33.png\"",
            "code": "async function(){\n        await driver.sleep(300)\n.wait('//div[text()=\"UI自动化新建合作商...\"]', 30000)\n               .sleep(300)\n.mouseMove(81, 10)\n.mouseMove(81, 10)\n.mouseUp(0);",
            "uuid": "cdc93062-05bd-42c2-8e6f-aac6e2ada95d",
            "skipped": false
          },
          {
            "title": "click: 合作商品管理 ( #container div.hetBeauty-list-header-filter, 96, 8, 0 )",
            "fullTitle": "sample/testx : chrome -- click: 合作商品管理 ( #container div.hetBeauty-list-header-filter, 96, 8, 0 )",
            "duration": 655,
            "state": "passed",
            "pass": true,
            "fail": false,
            "pending": false,
            "context": "\"./screenshots/sample/testx_chrome_34.png\"",
            "code": "async function(){\n        await driver.sleep(300)\n.wait('#container div.hetBeauty-list-header-filter', 30000)\n               .sleep(300)\n.mouseMove(96, 8)\n.click(0);",
            "uuid": "e13f062b-b71b-4259-b61a-2e3aaefc4342",
            "skipped": false
          },
          {
            "title": "mouseDown: UI自动化新建合作商..... ( //div[text()=\"UI自动化新建合作商...\"], 81, 13, 0 )",
            "fullTitle": "sample/testx : chrome -- mouseDown: UI自动化新建合作商..... ( //div[text()=\"UI自动化新建合作商...\"], 81, 13, 0 )",
            "duration": 641,
            "state": "passed",
            "pass": true,
            "fail": false,
            "pending": false,
            "context": "\"./screenshots/sample/testx_chrome_35.png\"",
            "code": "async function(){\n        await driver.sleep(300)\n.wait('//div[text()=\"UI自动化新建合作商...\"]', 30000)\n               .sleep(300)\n.mouseMove(81, 13)\n.mouseDown(0);",
            "uuid": "4ff38761-65e0-427e-b081-84c4a4486c72",
            "skipped": false
          },
          {
            "title": "mouseUp: UI自动化新建合作商..... ( //div[text()=\"UI自动化新建合作商...\"], 2, 3, 0 )",
            "fullTitle": "sample/testx : chrome -- mouseUp: UI自动化新建合作商..... ( //div[text()=\"UI自动化新建合作商...\"], 2, 3, 0 )",
            "duration": 677,
            "state": "passed",
            "pass": true,
            "fail": false,
            "pending": false,
            "context": "\"./screenshots/sample/testx_chrome_36.png\"",
            "code": "async function(){\n        await driver.sleep(300)\n.wait('//div[text()=\"UI自动化新建合作商...\"]', 30000)\n               .sleep(300)\n.mouseMove(2, 3)\n.mouseMove(2, 3)\n.mouseUp(0);",
            "uuid": "a90a84b5-7e18-4909-a830-c20704673431",
            "skipped": false
          },
          {
            "title": "click: #container div.main, 113, 1, 0",
            "fullTitle": "sample/testx : chrome -- click: #container div.main, 113, 1, 0",
            "duration": 657,
            "state": "passed",
            "pass": true,
            "fail": false,
            "pending": false,
            "context": "\"./screenshots/sample/testx_chrome_37.png\"",
            "code": "async function(){\n        await driver.sleep(300)\n.wait('#container div.main', 30000)\n               .sleep(300)\n.mouseMove(113, 1)\n.click(0);",
            "uuid": "9536b4b1-8486-43b7-8992-c724b09aa0df",
            "skipped": false
          },
          {
            "title": "click: #container th:nth-child(4) > i.ant-dropdown-trigger, 10, 34, 0",
            "fullTitle": "sample/testx : chrome -- click: #container th:nth-child(4) > i.ant-dropdown-trigger, 10, 34, 0",
            "duration": 654,
            "state": "passed",
            "pass": true,
            "fail": false,
            "pending": false,
            "context": "\"./screenshots/sample/testx_chrome_38.png\"",
            "code": "async function(){\n        await driver.sleep(300)\n.wait('#container th:nth-child(4) > i.ant-dropdown-trigger', 30000)\n               .sleep(300)\n.mouseMove(10, 34)\n.click(0);",
            "uuid": "adc18698-4abe-4cbb-80e9-e1dfc449e247",
            "skipped": false
          },
          {
            "title": "click: input.ant-input, 112, 2, 0",
            "fullTitle": "sample/testx : chrome -- click: input.ant-input, 112, 2, 0",
            "duration": 639,
            "state": "passed",
            "pass": true,
            "fail": false,
            "pending": false,
            "context": "\"./screenshots/sample/testx_chrome_39.png\"",
            "code": "async function(){\n        await driver.sleep(300)\n.wait('input.ant-input', 30000)\n               .sleep(300)\n.mouseMove(112, 2)\n.click(0);",
            "uuid": "7334a1af-6cec-47b2-afd2-1030db5f3c2a",
            "skipped": false
          },
          {
            "title": "sendKeys: UI自动化新建",
            "fullTitle": "sample/testx : chrome -- sendKeys: UI自动化新建",
            "duration": 21,
            "state": "passed",
            "pass": true,
            "fail": false,
            "pending": false,
            "context": "\"./screenshots/sample/testx_chrome_40.png\"",
            "code": "async function(){\n        await driver.sendKeys('UI自动化新建');",
            "uuid": "4d1676f8-3f4d-48df-8614-35bc29bb14d3",
            "skipped": false
          },
          {
            "title": "click: 确 定 ( div.hetBeauty-filter-btns > button[type=\"button\"].ant-btn-primary, 56, 5, 0 )",
            "fullTitle": "sample/testx : chrome -- click: 确 定 ( div.hetBeauty-filter-btns > button[type=\"button\"].ant-btn-primary, 56, 5, 0 )",
            "duration": 695,
            "state": "passed",
            "pass": true,
            "fail": false,
            "pending": false,
            "context": "\"./screenshots/sample/testx_chrome_41.png\"",
            "code": "async function(){\n        await driver.sleep(300)\n.wait('div.hetBeauty-filter-btns > button[type=\"button\"].ant-btn-primary', 30000)\n               .sleep(300)\n.mouseMove(56, 5)\n.click(0);",
            "uuid": "19f4dede-5455-4883-b035-86eed9c22d76",
            "skipped": false
          },
          {
            "title": "expect: text, //div[text()=\"UI自动化新建合作商...\"], equal, UI自动化新建合作商...",
            "fullTitle": "sample/testx : chrome -- expect: text, //div[text()=\"UI自动化新建合作商...\"], equal, UI自动化新建合作商...",
            "duration": 324,
            "state": "passed",
            "pass": true,
            "fail": false,
            "pending": false,
            "context": "\"./screenshots/sample/testx_chrome_42.png\"",
            "code": "async function(){\n        await driver.sleep(300)\n.wait('//div[text()=\"UI自动化新建合作商...\"]', 30000)\n            .text()\n            .should.not.be.a('error')\n            .should.equal(_(`UI自动化新建合作商...`));",
            "uuid": "8235322c-75d1-4d6c-8e5f-91b80935fa2e",
            "skipped": false
          },
          {
            "title": "click: #container div.hetBeauty-last-filter > section.hetBeauty-filter-item > i.hetBeauty-filter-delete > svg, 4, 9, 0",
            "fullTitle": "sample/testx : chrome -- click: #container div.hetBeauty-last-filter > section.hetBeauty-filter-item > i.hetBeauty-filter-delete > svg, 4, 9, 0",
            "duration": 667,
            "state": "passed",
            "pass": true,
            "fail": false,
            "pending": false,
            "context": "\"./screenshots/sample/testx_chrome_43.png\"",
            "code": "async function(){\n        await driver.sleep(300)\n.wait('#container div.hetBeauty-last-filter > section.hetBeauty-filter-item > i.hetBeauty-filter-delete > svg', 30000)\n               .sleep(300)\n.mouseMove(4, 9)\n.click(0);",
            "uuid": "0f8a6072-87d2-4c0a-820b-be64ecef0120",
            "skipped": false
          },
          {
            "title": "click: 上架 ( #container tr:nth-child(1) > td:nth-child(8) > span > span:nth-child(1), 20, 11, 0 )",
            "fullTitle": "sample/testx : chrome -- click: 上架 ( #container tr:nth-child(1) > td:nth-child(8) > span > span:nth-child(1), 20, 11, 0 )",
            "duration": 655,
            "state": "passed",
            "pass": true,
            "fail": false,
            "pending": false,
            "context": "\"./screenshots/sample/testx_chrome_44.png\"",
            "code": "async function(){\n        await driver.sleep(300)\n.wait('#container tr:nth-child(1) > td:nth-child(8) > span > span:nth-child(1)', 30000)\n               .sleep(300)\n.mouseMove(20, 11)\n.click(0);",
            "uuid": "c500481e-172b-423d-9ec4-fe55e279de4b",
            "skipped": false
          },
          {
            "title": "click: 确 认 ( div.ant-modal-footer > button[type=\"button\"].ant-btn-primary, 28, 10, 0 )",
            "fullTitle": "sample/testx : chrome -- click: 确 认 ( div.ant-modal-footer > button[type=\"button\"].ant-btn-primary, 28, 10, 0 )",
            "duration": 654,
            "state": "passed",
            "pass": true,
            "fail": false,
            "pending": false,
            "context": "\"./screenshots/sample/testx_chrome_45.png\"",
            "code": "async function(){\n        await driver.sleep(300)\n.wait('div.ant-modal-footer > button[type=\"button\"].ant-btn-primary', 30000)\n               .sleep(300)\n.mouseMove(28, 10)\n.click(0);",
            "uuid": "e65c5a93-ccba-41cd-85f6-73e339348fef",
            "skipped": false
          },
          {
            "title": "scrollElementTo: #container section > section.ant-layout, 0, 151",
            "fullTitle": "sample/testx : chrome -- scrollElementTo: #container section > section.ant-layout, 0, 151",
            "duration": 629,
            "state": "passed",
            "pass": true,
            "fail": false,
            "pending": false,
            "context": "\"./screenshots/sample/testx_chrome_46.png\"",
            "code": "async function(){\n        await driver.sleep(300)\n.wait('#container section > section.ant-layout', 30000)\n               .sleep(300)\n.scrollElementTo(0, 151);",
            "uuid": "4f065d03-4079-4375-aa2e-efc20121ac3a",
            "skipped": false
          },
          {
            "title": "click: 上架商品 ( //div[text()=\"上架商品\"], 47, 24, 0 )",
            "fullTitle": "sample/testx : chrome -- click: 上架商品 ( //div[text()=\"上架商品\"], 47, 24, 0 )",
            "duration": 672,
            "state": "passed",
            "pass": true,
            "fail": false,
            "pending": false,
            "context": "\"./screenshots/sample/testx_chrome_47.png\"",
            "code": "async function(){\n        await driver.sleep(300)\n.wait('//div[text()=\"上架商品\"]', 30000)\n               .sleep(300)\n.mouseMove(47, 24)\n.click(0);",
            "uuid": "a54e2b93-1972-425e-a819-1c2a332622e9",
            "skipped": false
          },
          {
            "title": "click: 门店授权 ( #container tr:nth-child(1) > td:nth-child(8) > span > span:nth-child(2) > span.blue_font, 43, 5, 0 )",
            "fullTitle": "sample/testx : chrome -- click: 门店授权 ( #container tr:nth-child(1) > td:nth-child(8) > span > span:nth-child(2) > span.blue_font, 43, 5, 0 )",
            "duration": 668,
            "state": "passed",
            "pass": true,
            "fail": false,
            "pending": false,
            "context": "\"./screenshots/sample/testx_chrome_48.png\"",
            "code": "async function(){\n        await driver.sleep(300)\n.wait('#container tr:nth-child(1) > td:nth-child(8) > span > span:nth-child(2) > span.blue_font', 30000)\n               .sleep(300)\n.mouseMove(43, 5)\n.click(0);",
            "uuid": "768fcefc-ea0b-4e18-a0ac-64df1da28788",
            "skipped": false
          },
          {
            "title": "click: 授权 ( tr:nth-child(1) > td:nth-child(5) > span > span.blue_font, 19, 3, 0 )",
            "fullTitle": "sample/testx : chrome -- click: 授权 ( tr:nth-child(1) > td:nth-child(5) > span > span.blue_font, 19, 3, 0 )",
            "duration": 672,
            "state": "passed",
            "pass": true,
            "fail": false,
            "pending": false,
            "context": "\"./screenshots/sample/testx_chrome_49.png\"",
            "code": "async function(){\n        await driver.sleep(300)\n.wait('tr:nth-child(1) > td:nth-child(5) > span > span.blue_font', 30000)\n               .sleep(300)\n.mouseMove(19, 3)\n.click(0);",
            "uuid": "e99baa67-2f02-4b9d-8e8e-9e67acc9690e",
            "skipped": false
          },
          {
            "title": "sendKeys: 123",
            "fullTitle": "sample/testx : chrome -- sendKeys: 123",
            "duration": 14,
            "state": "passed",
            "pass": true,
            "fail": false,
            "pending": false,
            "context": "\"./screenshots/sample/testx_chrome_50.png\"",
            "code": "async function(){\n        await driver.sendKeys('123');",
            "uuid": "ecabada4-2c2d-4f55-ba72-762fb8974c52",
            "skipped": false
          },
          {
            "title": "click: div.ant-modal-body > div > div.product-online-headder > div.hetBeauty-list-header, 885, 32, 0",
            "fullTitle": "sample/testx : chrome -- click: div.ant-modal-body > div > div.product-online-headder > div.hetBeauty-list-header, 885, 32, 0",
            "duration": 647,
            "state": "passed",
            "pass": true,
            "fail": false,
            "pending": false,
            "context": "\"./screenshots/sample/testx_chrome_51.png\"",
            "code": "async function(){\n        await driver.sleep(300)\n.wait('div.ant-modal-body > div > div.product-online-headder > div.hetBeauty-list-header', 30000)\n               .sleep(300)\n.mouseMove(885, 32)\n.click(0);",
            "uuid": "e15bcc65-5fa2-4f7e-bf9e-eab865924fdb",
            "skipped": false
          },
          {
            "title": "click: div:nth-child(14) > div.ant-modal-root > div[role=\"dialog\"].ant-modal-centered > div[role=\"document\"].ant-modal > div.ant-modal-content > button[type=\"button\"].ant-modal-close > span.ant-modal-close-x > i.ant-modal-close-icon > svg > path, 6, 7, 0",
            "fullTitle": "sample/testx : chrome -- click: div:nth-child(14) > div.ant-modal-root > div[role=\"dialog\"].ant-modal-centered > div[role=\"document\"].ant-modal > div.ant-modal-content > button[type=\"button\"].ant-modal-close > span.ant-modal-close-x > i.ant-modal-close-icon > svg > path, 6, 7, 0",
            "duration": 638,
            "state": "passed",
            "pass": true,
            "fail": false,
            "pending": false,
            "context": "\"./screenshots/sample/testx_chrome_52.png\"",
            "code": "async function(){\n        await driver.sleep(300)\n.wait('div:nth-child(14) > div > div.ant-modal-wrap.ant-modal-centered > div > div.ant-modal-content > button > span > i > svg > path', 50000)\n               .sleep(300)\n.mouseMove(6, 7)\n.click(0);",
            "uuid": "802bef82-f234-4b24-a488-9f9134842c52",
            "skipped": false
          }
        ],
        "pending": [],
        "_beforeEach": [
          {
            "title": "\"before each\" hook",
            "body": "function(){\n                let self = this;\n                self.stepId ++;\n                if(self.skipAll){\n                    self.skip();\n                }\n            }",
            "async": 0,
            "sync": true,
            "_timeout": 600000,
            "_slow": 1000,
            "_enableTimeouts": true,
            "timedOut": false,
            "_retries": -1,
            "_currentRetry": 0,
            "pending": false,
            "type": "hook",
            "parent": "~suites~suites~0",
            "ctx": "~suites~suites~0~ctx",
            "file": "E:\\test13\\sample\\testx.js",
            "_events": {},
            "_eventsCount": 1,
            "duration": 0,
            "_error": null
          }
        ],
        "_beforeAll": [
          {
            "title": "\"before all\" hook",
            "body": "function(){\n                let self = this;\n                let driver = new JWebDriver({\n                    'host': host,\n                    'port': port\n                });\n                let sessionConfig = Object.assign({}, webdriverConfig, {\n                    'group': group,\n                    'browserName': browserName,\n                    'version': browserVersion,\n                    'ie.ensureCleanSession': true,\n                });\n                if(proxy){\n                    sessionConfig.proxy = {\n                        'proxyType': 'manual',\n                        'httpProxy': proxy,\n                        'sslProxy': proxy\n                    }\n                }\n                else if(hosts){\n                    sessionConfig.hosts = hosts;\n                }\n\n                try {\n                    self.driver = driver.session(sessionConfig).maximize().config({\n                        pageloadTimeout: 30000, // page onload timeout\n                        scriptTimeout: 5000, // sync script timeout\n                        asyncScriptTimeout: 10000 // async script timeout\n                    });\n                } catch (e) {\n                    console.log(e);\n                }\n\n                self.testVars = testVars;\n                let casePath = path.dirname(caseName);\n                if (config.reporter && config.reporter.distDir) {\n                    self.screenshotPath = config.reporter.distDir + '/reports/screenshots/' + casePath;\n                    self.diffbasePath = config.reporter.distDir + '/reports/diffbase/' + casePath;\n                } else {\n                    self.screenshotPath = rootPath + '/reports/screenshots/' + casePath;\n                    self.diffbasePath = rootPath + '/reports/diffbase/' + casePath;\n                }\n                self.caseName = caseName.replace(/.*\\//g, '').replace(/\\s*[:\\.\\:\\-\\s]\\s*/g, '_');\n                mkdirs(self.screenshotPath);\n                mkdirs(self.diffbasePath);\n                self.stepId = 0;\n                return self.driver;\n            }",
            "async": 0,
            "sync": true,
            "_timeout": 600000,
            "_slow": 1000,
            "_enableTimeouts": true,
            "timedOut": false,
            "_retries": -1,
            "_currentRetry": 0,
            "pending": false,
            "type": "hook",
            "parent": "~suites~suites~0",
            "ctx": "~suites~suites~0~ctx",
            "file": "E:\\test13\\sample\\testx.js",
            "_events": {},
            "_eventsCount": 1,
            "timer": {
              "_called": false,
              "_idleTimeout": -1,
              "_idlePrev": null,
              "_idleNext": null,
              "_idleStart": 12191,
              "_onTimeout": null,
              "_repeat": null,
              "_destroyed": false
            },
            "duration": 11313,
            "_error": null
          },
          {
            "title": "\"before all\" hook",
            "body": "function(){\n        let self = this;\n        driver = self.driver;\n        testVars = self.testVars;\n    }",
            "async": 0,
            "sync": true,
            "_timeout": 600000,
            "_slow": 1000,
            "_enableTimeouts": true,
            "timedOut": false,
            "_retries": -1,
            "_currentRetry": 0,
            "pending": false,
            "type": "hook",
            "parent": "~suites~suites~0",
            "ctx": "~suites~suites~0~ctx",
            "file": "E:\\test13\\sample\\testx.js",
            "_events": {},
            "_eventsCount": 1,
            "duration": 0,
            "_error": null
          }
        ],
        "_afterEach": [
          {
            "title": "\"after each\" hook",
            "body": "async function(){\n                let self = this;\n                let currentTest = self.currentTest;\n                let title = currentTest.title;\n                if(currentTest.state === 'failed' && /^(url|waitBody|switchWindow|switchFrame):/.test(title)){\n                    self.skipAll = true;\n                }\n\n                if ((config.screenshots && config.screenshots.captureAll && !/^(closeWindow):/.test(title)) || currentTest.state === 'failed') {\n                    const casePath = path.dirname(caseName);\n                    const filepath = `${self.screenshotPath}/${self.caseName}_${self.stepId}`;\n                    const relativeFilePath = `./screenshots/${casePath}/${self.caseName}_${self.stepId}`;\n                    let driver = self.driver;\n                    try{\n                        // catch error when get alert msg\n                        await driver.getScreenshot(filepath + '.png');\n                        let url = await driver.url();\n                        let html = await driver.source();\n                        html = '<!--url: '+url+' -->\\n' + html;\n                        fs.writeFileSync(filepath + '.html', html);\n                        let cookies = await driver.cookies();\n                        fs.writeFileSync(filepath + '.cookie', JSON.stringify(cookies));\n                        appendToContext(self, relativeFilePath + '.png');\n                    }\n                    catch(e){}\n                }\n            }",
            "async": 0,
            "sync": true,
            "_timeout": 600000,
            "_slow": 1000,
            "_enableTimeouts": true,
            "timedOut": false,
            "_retries": -1,
            "_currentRetry": 0,
            "pending": false,
            "type": "hook",
            "parent": "~suites~suites~0",
            "ctx": "~suites~suites~0~ctx",
            "file": "E:\\test13\\sample\\testx.js",
            "_events": {},
            "_eventsCount": 1,
            "timer": {
              "_called": false,
              "_idleTimeout": -1,
              "_idlePrev": null,
              "_idleNext": null,
              "_idleStart": 81451,
              "_onTimeout": null,
              "_repeat": null,
              "_destroyed": false
            },
            "duration": 385,
            "_error": null
          }
        ],
        "_afterAll": [
          "~suites~suites~0~ctx~_runnable"
        ],
        "root": false,
        "_timeout": 600000,
        "_enableTimeouts": true,
        "_slow": 1000,
        "_bail": true,
        "_retries": -1,
        "_onlyTests": [],
        "_onlySuites": [],
        "delayed": false,
        "parent": "~suites",
        "file": "\\sample\\testx.js",
        "uuid": "532149aa-22ea-48c5-88eb-d0528969400f",
        "fullFile": "E:\\test13\\sample\\testx.js",
        "passes": [
          "~suites~suites~0~tests~0",
          "~suites~suites~0~tests~1",
          "~suites~suites~0~tests~2",
          "~suites~suites~0~tests~3",
          "~suites~suites~0~tests~4",
          "~suites~suites~0~tests~5",
          "~suites~suites~0~tests~6",
          "~suites~suites~0~tests~7",
          "~suites~suites~0~tests~8",
          "~suites~suites~0~tests~9",
          "~suites~suites~0~tests~10",
          "~suites~suites~0~tests~11",
          "~suites~suites~0~tests~12",
          "~suites~suites~0~tests~13",
          "~suites~suites~0~tests~14",
          "~suites~suites~0~tests~15",
          "~suites~suites~0~tests~16",
          "~suites~suites~0~tests~17",
          "~suites~suites~0~tests~18",
          "~suites~suites~0~tests~19",
          "~suites~suites~0~tests~20",
          "~suites~suites~0~tests~21",
          "~suites~suites~0~tests~22",
          "~suites~suites~0~tests~23",
          "~suites~suites~0~tests~24",
          "~suites~suites~0~tests~25",
          "~suites~suites~0~tests~26",
          "~suites~suites~0~tests~27",
          "~suites~suites~0~tests~28",
          "~suites~suites~0~tests~29",
          "~suites~suites~0~tests~30",
          "~suites~suites~0~tests~31",
          "~suites~suites~0~tests~32",
          "~suites~suites~0~tests~33",
          "~suites~suites~0~tests~34",
          "~suites~suites~0~tests~35",
          "~suites~suites~0~tests~36",
          "~suites~suites~0~tests~37",
          "~suites~suites~0~tests~38",
          "~suites~suites~0~tests~39",
          "~suites~suites~0~tests~40",
          "~suites~suites~0~tests~41",
          "~suites~suites~0~tests~42",
          "~suites~suites~0~tests~43",
          "~suites~suites~0~tests~44",
          "~suites~suites~0~tests~45",
          "~suites~suites~0~tests~46",
          "~suites~suites~0~tests~47",
          "~suites~suites~0~tests~48",
          "~suites~suites~0~tests~49",
          "~suites~suites~0~tests~50",
          "~suites~suites~0~tests~51"
        ],
        "failures": [],
        "skipped": [],
        "totalTests": 52,
        "totalPasses": 52,
        "totalFailures": 0,
        "totalPending": 0,
        "totalSkipped": 0,
        "duration": 34680
      }
    ],
    "tests": [],
    "pending": [],
    "_beforeEach": [],
    "_beforeAll": [],
    "_afterEach": [],
    "_afterAll": [],
    "root": true,
    "_timeout": 2000,
    "_enableTimeouts": true,
    "_slow": 75,
    "_bail": true,
    "_retries": -1,
    "_onlyTests": [],
    "_onlySuites": [],
    "delayed": false,
    "_events": {
      "pre-require": [
        null,
        null,
        null,
        null
      ]
    },
    "_eventsCount": 1,
    "uuid": "351b3370-5629-4125-9f7b-4dfe5d09fbdc",
    "fullFile": "",
    "file": "",
    "passes": [],
    "failures": [],
    "skipped": [],
    "totalTests": 0,
    "totalPasses": 0,
    "totalFailures": 0,
    "totalPending": 0,
    "totalSkipped": 0,
    "duration": 0,
    "_totalTime": 34680
  }
}